qframelesswindow/__init__.py
qframelesswindow/rc/__init__.py
qframelesswindow/rc/resource.py
qframelesswindow/titlebar/__init__.py
qframelesswindow/titlebar/title_bar_buttons.py
qframelesswindow/unix/__init__.py
qframelesswindow/unix/window_effect.py
qframelesswindow/utils/__init__.py
qframelesswindow/utils/linux_utils.py
qframelesswindow/utils/win32_utils.py
qframelesswindow/windows/__init__.py
qframelesswindow/windows/c_structures.py
qframelesswindow/windows/window_effect.py
PySide6_Frameless_Window-0.0.16.dist-info/LICENSE
PySide6_Frameless_Window-0.0.16.dist-info/METADATA
PySide6_Frameless_Window-0.0.16.dist-info/WHEEL
PySide6_Frameless_Window-0.0.16.dist-info/top_level.txt
PySide6_Frameless_Window-0.0.16.dist-info/RECORD
