Metadata-Version: 2.1
Name: PySide6-Frameless-Window
Version: 0.0.16
Summary: Based off PyQt5-Frameless-Window but migrated to PySide6.
Home-page: https://github.com/rayzchen/PySide6-Frameless-Window
Author: Ray Chen
Author-email: tankimarshal2@gmail.com
License: MIT
Keywords: pyside6 frameless
Platform: UNKNOWN
Classifier: Programming Language :: Python :: 3
Classifier: License :: OSI Approved :: MIT License
Classifier: Operating System :: OS Independent
License-File: LICENSE
Requires-Dist: PySide6
Requires-Dist: xcffib ; platform_system != "Windows"
Requires-Dist: pywin32 ; platform_system == "Windows"
